bowler/__init__.py
bowler/helpers.py
bowler/imr.py
bowler/query.py
bowler/tool.py
bowler/type_inference.py
bowler/types.py
fissix/Grammar.txt
fissix/PatternGrammar.txt
fissix/__init__.py
fissix/btm_matcher.py
fissix/btm_utils.py
fissix/fixer_base.py
fissix/fixer_util.py
fissix/patcomp.py
fissix/pygram.py
fissix/pytree.py
fissix/refactor.py
fissix/pgen2/__init__.py
fissix/pgen2/conv.py
fissix/pgen2/driver.py
fissix/pgen2/grammar.py
fissix/pgen2/literals.py
fissix/pgen2/parse.py
fissix/pgen2/pgen.py
fissix/pgen2/token.py
fissix/pgen2/tokenize.py
paddle1to2/__init__.py
paddle1to2/__main__.py
paddle1to2/common.py
paddle1to2/filters.py
paddle1to2/fixers.py
paddle1to2/main.py
paddle1to2/processors.py
paddle1to2/refactor.py
paddle1to2/spec.py
paddle1to2/transformers.py
paddle1to2/utils.py
paddle1to2/tests/__init__.py
paddle1to2/tests/test_refactor.py
tools/__init__.py
tools/click.py
tools/find_match_node.py
tools/find_pattern.py
paddle1to2-0.0.28.dist-info/LICENSE
paddle1to2-0.0.28.dist-info/METADATA
paddle1to2-0.0.28.dist-info/WHEEL
paddle1to2-0.0.28.dist-info/entry_points.txt
paddle1to2-0.0.28.dist-info/top_level.txt
paddle1to2-0.0.28.dist-info/RECORD
