Metadata-Version: 2.1
Name: paddle1to2
Version: 0.0.28
Summary: Upgrade python project from paddle-1.x to paddle-2.0
Home-page: https://github.com/PaddlePaddle/paddle1to2
Author: T8T9, PaddlePaddle
Author-email: taoshibo@baidu.com
License: Apache License 2.0
Keywords: paddle1to2,paddle,paddlepaddle
Platform: UNKNOWN
Classifier: License :: OSI Approved
Classifier: Programming Language :: Python :: 3
Classifier: Programming Language :: Python :: 3.5
Classifier: Programming Language :: Python :: 3.6
Classifier: Programming Language :: Python :: 3.7
Classifier: Programming Language :: Python :: 3.8
Classifier: Operating System :: OS Independent
Requires-Python: >=3.5.4
